agent_reader/__init__.py
agent_reader/link_type.py
agent_reader/reader.py
agent_reader-0.2.2.dist-info/LICENSE
agent_reader-0.2.2.dist-info/METADATA
agent_reader-0.2.2.dist-info/WHEEL
agent_reader-0.2.2.dist-info/RECORD
